setup.py
snipperconvertor.egg-info/PKG-INFO
snipperconvertor.egg-info/SOURCES.txt
snipperconvertor.egg-info/dependency_links.txt
snipperconvertor.egg-info/top_level.txt
snippetconvertor/__init__.py