Metadata-Version: 2.1
Name: snipperconvertor
Version: 0.0.2
Summary: VScode  snippet & Eclipse Template convertor
Author: AndyZhu
Author-email: andyzhu@live.com
